Metadata-Version: 1.0
Name: fst-cantools
Version: 0.8
Summary: CAN library for FST Lisboa
Home-page: https://github.com/joajfreitas/fcp
Author: Joao Freitas
Author-email: joaj.freitas@gmail.com
License: GPLv3
Platform: UNKNOWN
